ansible_playbill/__init__.py
ansible_playbill/py.typed
ansible_playbill-0.4.0.dist-info/LICENSE
ansible_playbill-0.4.0.dist-info/METADATA
ansible_playbill-0.4.0.dist-info/WHEEL
ansible_playbill-0.4.0.dist-info/top_level.txt
ansible_playbill-0.4.0.dist-info/RECORD
